marlo/__init__.py
marlo/api/__init__.py
marlo/api/dashboard/__init__.py
marlo/api/dashboard/app.py
marlo/api/dashboard/common.py
marlo/api/dashboard/routes/__init__.py
marlo/api/dashboard/routes/agents.py
marlo/api/dashboard/routes/copilot.py
marlo/api/dashboard/routes/learnings.py
marlo/api/dashboard/routes/search.py
marlo/api/dashboard/routes/sessions.py
marlo/api/dashboard/routes/stats.py
marlo/api/dashboard/routes/tasks.py
marlo/api/feedback/__init__.py
marlo/api/feedback/routes.py
marlo/api/ingest/__init__.py
marlo/api/ingest/routes.py
marlo/billing/__init__.py
marlo/billing/client.py
marlo/cli/__init__.py
marlo/cli/migrate.py
marlo/core/__init__.py
marlo/core/digest.py
marlo/core/ids.py
marlo/core/interfaces.py
marlo/core/json_utils.py
marlo/core/sentry.py
marlo/core/config/__init__.py
marlo/core/config/models.py
marlo/feedback/__init__.py
marlo/feedback/chunk_updater.py
marlo/feedback/prompts.py
marlo/learning/__init__.py
marlo/learning/experiments/__init__.py
marlo/learning/generation/__init__.py
marlo/learning/generation/compiler.py
marlo/learning/generation/generator.py
marlo/learning/generation/prompts.py
marlo/learning/management/__init__.py
marlo/learning/management/compression.py
marlo/learning/management/context_manager.py
marlo/learning/management/learning_history.py
marlo/learning/management/lifecycle.py
marlo/learning/management/pipeline.py
marlo/learning/management/playbook.py
marlo/learning/management/session_state.py
marlo/learning/management/usage.py
marlo/learning/management/memory/base.py
marlo/learning/management/memory/schema.py
marlo/learning/management/memory/trace_memory.py
marlo/learning/rewards/__init__.py
marlo/learning/rewards/drift.py
marlo/learning/rewards/runner.py
marlo/learning/rewards/judges/__init__.py
marlo/learning/rewards/judges/base.py
marlo/learning/rewards/judges/prompts.py
marlo/measurement/__init__.py
marlo/measurement/metrics/__init__.py
marlo/measurement/reports/__init__.py
marlo_sdk-0.0.5.dist-info/licenses/LICENSE
marlo_sdk-0.0.5.dist-info/METADATA
marlo_sdk-0.0.5.dist-info/WHEEL
marlo_sdk-0.0.5.dist-info/entry_points.txt
marlo_sdk-0.0.5.dist-info/top_level.txt
marlo_sdk-0.0.5.dist-info/RECORD
