Metadata-Version: 2.4
Name: marlo-sdk
Version: 0.0.5
Summary: The official Python SDK for Marlo - the agent learning platform
Keywords: autonomy,agents,reasoning,reward-models,trajectories,learning
Requires-Python: >=3.11
License-File: LICENSE
Requires-Dist: httpx
Requires-Dist: pydantic
Provides-Extra: platform
Requires-Dist: asyncpg; extra == "platform"
Requires-Dist: fastapi; extra == "platform"
Requires-Dist: python-dotenv; extra == "platform"
Requires-Dist: google-genai; extra == "platform"
Requires-Dist: importlib-resources; extra == "platform"
Requires-Dist: langgraph; extra == "platform"
Requires-Dist: langgraph-checkpoint-postgres; extra == "platform"
Requires-Dist: pydantic; extra == "platform"
Requires-Dist: sentry-sdk[fastapi]; extra == "platform"
Requires-Dist: sqlglot; extra == "platform"
Requires-Dist: uvicorn; extra == "platform"
Provides-Extra: dev
Requires-Dist: pytest; extra == "dev"
Requires-Dist: pytest-asyncio; extra == "dev"
Provides-Extra: tokenizer
Requires-Dist: tiktoken; extra == "tokenizer"
Dynamic: license-file
